unirank/__init__.py
unirank/rank/__init__.py
unirank/rank/usa_rank.py
unirank/rank/useragents.txt
uni_rank-1.0.2.dist-info/LICENSE
uni_rank-1.0.2.dist-info/METADATA
uni_rank-1.0.2.dist-info/WHEEL
uni_rank-1.0.2.dist-info/top_level.txt
uni_rank-1.0.2.dist-info/RECORD
