Metadata-Version: 2.1
Name: uni-rank
Version: 1.0.2
Summary: Get the ordered list of USA universities based on their latest ranking.
Home-page: https://github.com/nahid18/uni-rank
Author: Abdullah Al Nahid
Author-email: nahidpatwary1@gmail.com
License: GPLv3
Project-URL: Documentation, https://github.com/nahid18/uni-rank/blob/main/README.md
Keywords: ranking usa university
Platform: UNKNOWN
Classifier: Development Status :: 5 - Production/Stable
Classifier: License :: OSI Approved :: GNU General Public License v3 (GPLv3)
Classifier: Natural Language :: English
Classifier: Programming Language :: Python :: 3
Classifier: Programming Language :: Python :: 3.5
Classifier: Programming Language :: Python :: 3.6
Classifier: Programming Language :: Python :: 3.7
Classifier: Programming Language :: Python :: 3.8
Requires-Dist: requests
Requires-Dist: pandas
